lds_merkle_proof_2019/__init__.py
lds_merkle_proof_2019/mappings.py
lds_merkle_proof_2019/merkle_proof_2019.py
lds_merkle_proof_2019_bloxberg-0.0.7.dist-info/LICENSE
lds_merkle_proof_2019_bloxberg-0.0.7.dist-info/METADATA
lds_merkle_proof_2019_bloxberg-0.0.7.dist-info/WHEEL
lds_merkle_proof_2019_bloxberg-0.0.7.dist-info/top_level.txt
lds_merkle_proof_2019_bloxberg-0.0.7.dist-info/RECORD
