Metadata-Version: 2.1
Name: lds-merkle-proof-2019-bloxberg
Version: 0.0.7
Summary: MerkleProof2019 module for python
Home-page: https://github.com/crossoveranx/lds-merkle-proof-2019-py
Author: bloxberg
Author-email: info@bloxberg.org
License: MIT
Platform: UNKNOWN
Requires-Dist: py-multibase (>=1.0.1)
Requires-Dist: cbor2 (>=4.1.2)
